tkcalc/__init__.py
tkcalc/__main__.py
tkcalc/app.py
tkcalc/main.py
tkcalc/model.py
tkcalc-1.3.12.dist-info/METADATA
tkcalc-1.3.12.dist-info/WHEEL
tkcalc-1.3.12.dist-info/entry_points.txt
tkcalc-1.3.12.dist-info/top_level.txt
tkcalc-1.3.12.dist-info/RECORD
