Metadata-Version: 2.1
Name: tkcalc
Version: 1.3.12
Summary: Calcolatrice di base con tkinter
Home-page: https://test.pypi.org/project/tkcalc
Author: Elia S. Toselli
Author-email: elia.toselli@outlook.it
License: UNKNOWN
Platform: UNKNOWN
Requires: t
Requires: k
Requires: i
Requires: n
Requires: t
Requires: e
Requires: r
